atw/__init__.py
atw/version.py
atw-0.0.1.dist-info/LICENSE
atw-0.0.1.dist-info/METADATA
atw-0.0.1.dist-info/WHEEL
atw-0.0.1.dist-info/top_level.txt
atw-0.0.1.dist-info/RECORD
