Metadata-Version: 2.1
Name: atw
Version: 0.0.1
Summary: Check dutch working hours law compliance
Home-page: https://www.maanrijp.nl
Author: Arvid Hahné
Author-email: arvid@maanrijp.nl
License: GNU GPLv3
Platform: UNKNOWN
Classifier: Development Status :: 1 - Planning
Classifier: Intended Audience :: Science/Research
Classifier: Programming Language :: Python :: 3.7
License-File: LICENSE
